{
  "@id": "https://data.datatourisme.fr/38/9a690425-873b-38c8-88ba-ff25c43cff1d",
  "dc:identifier": "HLOb2cc4eae6bcb4",
  "@type": [
    "schema:Accommodation",
    "schema:LodgingBusiness",
    "Accommodation",
    "PlaceOfInterest",
    "PointOfInterest",
    "RentalAccommodation"
  ],
  "rdfs:label": {
    "fr": [
      "La Grange du Manoir de Kermain"
    ]
  },
  "availableLanguage": [
    "en",
    "fr",
    "it"
  ],
  "hasBeenCreatedBy": {
    "@id": "https://data.datatourisme.fr/38/dcfe7804-69c3-3120-af60-d01767ae7016",
    "dc:identifier": "c7bde102-16ce-48c7-a922-f28c15a908e5",
    "schema:address": [
      {
        "@id": "https://data.datatourisme.fr/98dd620c-f1cb-37ca-b347-c905279d004d",
        "schema:addressLocality": "Vannes",
        "schema:postalCode": "56038",
        "schema:streetAddress": [
          "2 RUE LOUIS DE BROGLIE"
        ],
        "@type": [
          "schema:PostalAddress",
          "PostalAddress"
        ],
        "hasAddressCity": {
          "@id": "kb:56260",
          "@type": [
            "City"
          ],
          "rdfs:label": {
            "de": [
              "Vannes"
            ],
            "pt": [
              "Vannes"
            ],
            "en": [
              "Vannes"
            ],
            "it": [
              "Vannes"
            ],
            "fr": [
              "Vannes"
            ],
            "nl": [
              "Vannes"
            ],
            "es": [
              "Vannes"
            ]
          },
          "insee": "56260",
          "isPartOfDepartment": {
            "@id": "kb:France5356",
            "@type": [
              "Department"
            ],
            "rdfs:label": {
              "de": [
                "Morbihan"
              ],
              "pt": [
                "Morbihan"
              ],
              "en": [
                "Morbihan"
              ],
              "it": [
                "Morbihan"
              ],
              "fr": [
                "Morbihan"
              ],
              "nl": [
                "Morbihan"
              ],
              "es": [
                "Morbihan"
              ]
            },
            "insee": "56",
            "isPartOfRegion": {
              "@id": "kb:France53",
              "@type": [
                "Region"
              ],
              "rdfs:label": {
                "de": [
                  "Bretagne"
                ],
                "pt": [
                  "Bretagne"
                ],
                "en": [
                  "Bretagne"
                ],
                "it": [
                  "Bretagne"
                ],
                "fr": [
                  "Bretagne"
                ],
                "nl": [
                  "Bretagne"
                ],
                "es": [
                  "Bretagne"
                ]
              },
              "insee": "53",
              "isPartOfCountry": {
                "@id": "kb:France",
                "@type": [
                  "schema:Country"
                ],
                "rdfs:label": {
                  "de": [
                    "France",
                    "Frankreich"
                  ],
                  "pt": [
                    "França",
                    "France"
                  ],
                  "en": [
                    "France"
                  ],
                  "it": [
                    "France",
                    "Francia"
                  ],
                  "fr": [
                    "France"
                  ],
                  "nl": [
                    "France",
                    "Frankrijk"
                  ],
                  "es": [
                    "France",
                    "Francia"
                  ]
                }
              }
            }
          }
        }
      }
    ],
    "schema:email": [
      "bd@morbihan.com"
    ],
    "schema:legalName": "ADT 56",
    "@type": [
      "schema:Organization",
      "foaf:Agent",
      "Agent"
    ],
    "foaf:homepage": [
      "https://www.morbihan.com/"
    ]
  },
  "hasBeenPublishedBy": [
    {
      "@id": "https://data.datatourisme.fr/fd02f0c8-35c6-3230-a6f5-574cb8fb2557",
      "schema:email": [
        "c-leux@tourismebretagne.com"
      ],
      "schema:legalName": "SIT Bretagne",
      "@type": [
        "schema:Organization",
        "foaf:Agent",
        "Agent"
      ],
      "foaf:homepage": [
        "https://www.tourismebretagne.com/"
      ]
    }
  ],
  "hasBookingContact": [
    {
      "@id": "https://data.datatourisme.fr/0c443402-eab1-3bcb-bb5c-557c7b23a68c",
      "schema:telephone": [
        "+33 2 57 18 00 00"
      ],
      "@type": [
        "foaf:Agent",
        "Agent"
      ],
      "foaf:homepage": [
        "http://www.gites-de-france.com/fr/bretagne/morbihan/la-grange-du-manoir-de-kermain-56g10017?adults=2&children=0&infants=0"
      ]
    }
  ],
  "hasContact": [
    {
      "@id": "https://data.datatourisme.fr/0c443402-eab1-3bcb-bb5c-557c7b23a68c",
      "schema:telephone": [
        "+33 2 57 18 00 00"
      ],
      "@type": [
        "foaf:Agent",
        "Agent"
      ],
      "foaf:homepage": [
        "http://www.gites-de-france.com/fr/bretagne/morbihan/la-grange-du-manoir-de-kermain-56g10017?adults=2&children=0&infants=0"
      ]
    },
    {
      "@id": "https://data.datatourisme.fr/73a1a566-519b-3597-9815-73ab91f437ec",
      "schema:legalName": "La Grange du Manoir de Kermain",
      "schema:telephone": [
        "+33 2 57 18 00 00"
      ],
      "@type": [
        "schema:Organization",
        "foaf:Agent",
        "Agent"
      ],
      "foaf:homepage": [
        "http://www.gites-de-france.com/fr/bretagne/morbihan/la-grange-du-manoir-de-kermain-56g10017?adults=2&children=0&infants=0"
      ]
    }
  ],
  "hasDescription": [
    {
      "@id": "https://data.datatourisme.fr/35118c2f-a996-3eda-80a5-a7a535d077c5",
      "dc:description": {
        "de": [
          "Hier befinden Sie sich auf dem Gelände des Manoir de Kermain, einem historischen Bauwerk aus dem 16. Die Besitzer, die sich für Geschichte, Tradition und alte Steine begeistern, werden Ihnen gerne ihr Anwesen zeigen. Lassen Sie sich nieder, nehmen Sie sich Zeit und lassen Sie sich von der Atmosphäre in einer grünen Umgebung verzaubern. Vom Zentrum der Bretagne aus können Sie Tagesausflüge zu den schönsten Orten unternehmen: den Golf von Morbihan und seine Inseln, den Mont Saint Michel, die rosa Granitküste, die Pointe du Raz und die Monts d'Arrée ...\nDiese Ferienunterkunft ist ein schönes Gebäude aus Stein aus dem 19. Jahrhundert mit großen Räumen. Sie ist unabhängig und von einem großen Garten umgeben, um Ihre Ruhe und die Sicherheit der Kinder zu gewährleisten.\n- Das Erdgeschoss bietet Ihnen einen großen Wohnraum mit voll ausgestatteter Küche, Wohn- und Esszimmer (Ofenheizung + elektrische Zusatzheizung) sowie ein Badezimmer mit WC.\n- Stock: 3 Schlafzimmer (ein Schlafzimmer mit einem 160 cm breiten Bett, ein Schlafzimmer mit zwei 90 cm breiten Betten und ein Schlafzimmer mit einem 90 cm breiten Bett), ein Badezimmer mit WC.\nEine Waschküche wurde eingerichtet (angrenzend an die Gite) und kann als Fahrrad-/Motorradunterstand genutzt werden. Privater Garten und Parkplatz."
        ],
        "en": [
          "Here you are on the grounds of Manoir de Kermain, a 16th-century historic monument. The owners, passionate about history, tradition and old stones, will be delighted to show you around their property. Relax, take your time and let yourself be seduced by the surrounding atmosphere, in a verdant setting. From central Brittany, you can set off on day trips to visit the most beautiful sites: the Gulf of Morbihan and its islands, Mont Saint Michel, the pink granite coast, the Pointe du Raz and the Monts d'Arrée...\nThis vacation rental is a beautiful, spacious 19th-century stone building. It is detached and surrounded by a large garden for your peace and quiet and the safety of your children.\n- On the first floor, you'll find a large living room with a fully-equipped kitchen, a sitting room and a shower room with toilet.\n- 1st floor: 3 bedrooms (one with 1 x 160cm bed, one with 2 x 90cm beds and one with 1 x 90cm bed), bathroom with toilet.\nA laundry room has been fitted out (adjoining the gite) and can be used as a bike/motorcycle shelter. Private garden and parking."
        ],
        "it": [
          "Si tratta della tenuta Manoir de Kermain, un monumento storico risalente al XVI secolo. I proprietari, appassionati di storia, tradizione e vecchie pietre, saranno lieti di mostrarvi la loro proprietà. Rilassatevi, prendetevi il vostro tempo e lasciatevi sedurre dall'atmosfera circostante, in un ambiente verdeggiante. Dal centro della Bretagna, potrete fare escursioni giornaliere per visitare i siti più belli: il Golfo di Morbihan e le sue isole, Mont Saint Michel, la costa di granito rosa, la Pointe du Raz e i Monts d'Arrée...\nQuesta casa vacanze è un bellissimo e spazioso edificio in pietra del XIX secolo. È indipendente e circondata da un ampio giardino per la vostra tranquillità e la sicurezza dei vostri bambini.\n- Al piano terra si trova un ampio soggiorno con cucina completamente attrezzata, un salotto (con stufa a legna e riscaldamento elettrico supplementare) e un bagno con doccia e WC.\n- 1° piano: 3 camere da letto (una con 1 letto da 160 cm, una con 2 letti da 90 cm e una con 1 letto da 90 cm), bagno con wc.\nUn ripostiglio è stato trasformato (adiacente all'alloggio) e può essere utilizzato come rimessa per biciclette/moto. Giardino privato e parcheggio."
        ],
        "fr": [
          "Ici, vous êtes sur le domaine du Manoir de Kermain, monument historique du XVIè siècle. Les propriétaires, passionnés d'histoire, de tradition et de vieilles pierres, vous feront découvrir avec plaisir leur propriété. Posez-vous, prenez le temps et laissez-vous séduire par l'atmosphère ambiante, dans un cadre verdoyant. Du centre Bretagne, vous pourrez partir pour des excursions à la journée pour visiter les plus beaux sites : le Golfe du Morbihan et ses îles, le Mont Saint Michel, la côte de granite rose, la pointe du Raz et les monts d'Arrée ...\nCette location de vacances est un beau bâtiment en pierre du XIXè siècle aux grands volumes. Elle est indépendante et entourée d'un grand jardin pour votre tranquillité et la sécurité des enfants.\n- Le rez-de-chaussée vous propose une vaste pièce de vie avec cuisine toute équipée, séjour et salon (chauffage au poêle + chauffage électrique d'appoint )ainsi qu'une salle d'eau avec wc. \n- Au 1er étage : 3 chambres (une chambre avec 1 lit en 160, une chambre avec 2 lits en 90 et une chambre avec 1 lit en 90), une salle de bains avec wc.\nUne buanderie a été aménagée (attenante au gite) et peut être utilisée comme abri vélos/motos. Jardin et parking privés."
        ],
        "es": [
          "Se trata de la finca Manoir de Kermain, un monumento histórico que data del siglo XVI. Los propietarios, apasionados de la historia, la tradición y las piedras antiguas, estarán encantados de mostrarle su propiedad. Relájese, tómese su tiempo y déjese seducir por el ambiente que le rodea, en un entorno verde. Desde el centro de Bretaña, podrá realizar excursiones de un día para visitar los lugares más bellos: el golfo de Morbihan y sus islas, el Mont Saint Michel, la costa de granito rosa, la Pointe du Raz y los Monts d'Arrée...\nEste alquiler de vacaciones es un hermoso y espacioso edificio de piedra del siglo XIX. Es independiente y está rodeado de un gran jardín para su tranquilidad y la seguridad de sus hijos.\n- En la planta baja, un gran salón con cocina totalmente equipada, una sala de estar (con estufa de leña y calefacción eléctrica adicional) y un cuarto de ducha con WC.\n- 1ª planta: 3 dormitorios (uno con 1 cama de 160 cm, uno con 2 camas de 90 cm y uno con 1 cama de 90 cm), cuarto de baño con wc.\nUn cuarto de servicio se ha convertido (junto a la casa rural) y se puede utilizar como una bicicleta / cobertizo moto. Jardín privado y aparcamiento."
        ],
        "nl": [
          "Dit is het landgoed Manoir de Kermain, een historisch monument uit de 16e eeuw. De eigenaars, die gepassioneerd zijn door geschiedenis, traditie en oude stenen, zullen je met plezier rondleiden op hun landgoed. Ontspan, neem de tijd en laat je verleiden door de omringende sfeer, in een groene omgeving. Vanuit het centrum van Bretagne kunt u dagtochten maken om de mooiste plekjes te bezoeken: de Golf van Morbihan en zijn eilanden, de Mont Saint Michel, de roze granietkust, de Pointe du Raz en de Monts d'Arrée...\nDeze vakantiewoning is een mooi, ruim stenen gebouw uit de 19e eeuw. Het is vrijstaand en omgeven door een grote tuin voor uw gemoedsrust en de veiligheid van uw kinderen.\n- Op de begane grond is er een grote woonkamer met een volledig uitgeruste keuken, een zitkamer (met houtkachel en extra elektrische verwarming) en een doucheruimte met toilet.\n- 1e verdieping: 3 slaapkamers (een met 1 bed van 160 cm, een met 2 bedden van 90 cm en een met 1 bed van 90 cm), badkamer met wc.\nEen bijkeuken is omgebouwd (grenzend aan de gîte) en kan gebruikt worden als fietsen- en motorstalling. Privétuin en parkeerplaats."
        ]
      },
      "@type": [
        "Description"
      ],
      "hasTranslatedProperty": [
        {
          "@id": "https://data.datatourisme.fr/0106b148-2172-330e-8e1c-afb9adaf0927",
          "dc:contributor": [
            "https://api.deepl.com/v2/translate"
          ],
          "rdf:language": [
            "en"
          ],
          "rdf:predicate": [
            {
              "@id": "dc:description"
            }
          ]
        },
        {
          "@id": "https://data.datatourisme.fr/23495877-4730-3687-a974-1f1eae8acb14",
          "dc:contributor": [
            "https://api.deepl.com/v2/translate"
          ],
          "rdf:language": [
            "nl"
          ],
          "rdf:predicate": [
            {
              "@id": "dc:description"
            }
          ]
        },
        {
          "@id": "https://data.datatourisme.fr/7c9482ca-e8a9-3808-aba8-11fb83ee3701",
          "dc:contributor": [
            "https://api.deepl.com/v2/translate"
          ],
          "rdf:language": [
            "de"
          ],
          "rdf:predicate": [
            {
              "@id": "dc:description"
            }
          ]
        },
        {
          "@id": "https://data.datatourisme.fr/99fdc920-a958-3ba2-95a4-f344fabea0dc",
          "dc:contributor": [
            "https://api.deepl.com/v2/translate"
          ],
          "rdf:language": [
            "es"
          ],
          "rdf:predicate": [
            {
              "@id": "dc:description"
            }
          ]
        },
        {
          "@id": "https://data.datatourisme.fr/9aadb23b-ced9-34b9-8dba-2bbb3861eab7",
          "dc:contributor": [
            "https://api.deepl.com/v2/translate"
          ],
          "rdf:language": [
            "it"
          ],
          "rdf:predicate": [
            {
              "@id": "dc:description"
            }
          ]
        }
      ]
    }
  ],
  "isLocatedAt": [
    {
      "@id": "https://data.datatourisme.fr/59d7b2f9-4dda-3985-8048-f025725fbc3e",
      "schema:address": [
        {
          "@id": "https://data.datatourisme.fr/cb479f72-0fdb-367d-a9d2-8705876e909f",
          "schema:addressLocality": "Langonnet",
          "schema:postalCode": "56630",
          "schema:streetAddress": [
            "Kermain"
          ],
          "@type": [
            "schema:PostalAddress",
            "PostalAddress"
          ],
          "hasAddressCity": {
            "@id": "kb:56100",
            "@type": [
              "City"
            ],
            "rdfs:label": {
              "de": [
                "Langonnet"
              ],
              "pt": [
                "Langonnet"
              ],
              "en": [
                "Langonnet"
              ],
              "it": [
                "Langonnet"
              ],
              "fr": [
                "Langonnet"
              ],
              "nl": [
                "Langonnet"
              ],
              "es": [
                "Langonnet"
              ]
            },
            "insee": "56100",
            "isPartOfDepartment": {
              "@id": "kb:France5356",
              "@type": [
                "Department"
              ],
              "rdfs:label": {
                "de": [
                  "Morbihan"
                ],
                "pt": [
                  "Morbihan"
                ],
                "en": [
                  "Morbihan"
                ],
                "it": [
                  "Morbihan"
                ],
                "fr": [
                  "Morbihan"
                ],
                "nl": [
                  "Morbihan"
                ],
                "es": [
                  "Morbihan"
                ]
              },
              "insee": "56",
              "isPartOfRegion": {
                "@id": "kb:France53",
                "@type": [
                  "Region"
                ],
                "rdfs:label": {
                  "de": [
                    "Bretagne"
                  ],
                  "pt": [
                    "Bretagne"
                  ],
                  "en": [
                    "Bretagne"
                  ],
                  "it": [
                    "Bretagne"
                  ],
                  "fr": [
                    "Bretagne"
                  ],
                  "nl": [
                    "Bretagne"
                  ],
                  "es": [
                    "Bretagne"
                  ]
                },
                "insee": "53",
                "isPartOfCountry": {
                  "@id": "kb:France",
                  "@type": [
                    "schema:Country"
                  ],
                  "rdfs:label": {
                    "de": [
                      "France",
                      "Frankreich"
                    ],
                    "pt": [
                      "França",
                      "France"
                    ],
                    "en": [
                      "France"
                    ],
                    "it": [
                      "France",
                      "Francia"
                    ],
                    "fr": [
                      "France"
                    ],
                    "nl": [
                      "France",
                      "Frankrijk"
                    ],
                    "es": [
                      "France",
                      "Francia"
                    ]
                  }
                }
              }
            }
          }
        }
      ],
      "schema:geo": {
        "@id": "https://data.datatourisme.fr/9fa2c1ff-ce80-3a4e-93e9-5ac1f29467a9",
        "schema:latitude": "48.1270079",
        "schema:longitude": "-3.4836752",
        "@type": [
          "schema:GeoCoordinates"
        ]
      },
      "schema:openingHoursSpecification": [
        {
          "@id": "https://data.datatourisme.fr/3dec4895-d6ec-3604-991b-5c25f540808c",
          "schema:validFrom": "2026-05-01T00:00:00",
          "schema:validThrough": "2026-10-01T00:00:00",
          "@type": [
            "schema:OpeningHoursSpecification"
          ]
        }
      ],
      "@type": [
        "schema:Place",
        "Place"
      ],
      "petsAllowed": true
    }
  ],
  "lastUpdate": "2026-03-18",
  "lastUpdateDatatourisme": "2026-03-19T04:22:22.198Z",
  "offers": [
    {
      "@id": "https://data.datatourisme.fr/45937faf-2105-38db-8ece-c32760916667",
      "schema:acceptedPaymentMethod": [
        {
          "@id": "kb:HolidayVouchers",
          "@type": [
            "schema:PaymentMethod"
          ],
          "rdfs:label": {
            "de": [
              "Urlaubsschecks"
            ],
            "pt": [
              "Vales de férias"
            ],
            "en": [
              "Holiday vouchers"
            ],
            "it": [
              "Buoni vacanza"
            ],
            "fr": [
              "Chèques vacances"
            ],
            "nl": [
              "Vakantiecheques"
            ],
            "es": [
              "Cheques de vacaciones"
            ]
          }
        },
        {
          "@id": "kb:Transfers",
          "@type": [
            "schema:PaymentMethod"
          ],
          "rdfs:label": {
            "de": [
              "Überweisungen"
            ],
            "pt": [
              "Transferências"
            ],
            "en": [
              "Transfers"
            ],
            "it": [
              "Bonifici"
            ],
            "fr": [
              "Virements"
            ],
            "es": [
              "Transferencias"
            ],
            "nl": [
              "Overschrijvingen"
            ]
          }
        }
      ],
      "@type": [
        "schema:Offer",
        "Offer"
      ]
    }
  ]
}