{
  "@id": "https://data.datatourisme.fr/38/c98ffc3d-4df4-3032-87af-26afe0b9289e",
  "dc:identifier": "ASC07dc552aa5324",
  "@type": [
    "schema:Product",
    "ActivityProvider",
    "LeisureSportActivityProvider",
    "PlaceOfInterest",
    "PointOfInterest",
    "Product",
    "SportsAndLeisurePlace"
  ],
  "rdfs:label": {
    "fr": [
      "Kerguélen Equitation"
    ]
  },
  "hasBeenCreatedBy": {
    "@id": "https://data.datatourisme.fr/cd27e4d8-de33-30c0-b201-2281f20f6c5e",
    "schema:legalName": "ADT 56",
    "@type": [
      "schema:Organization",
      "foaf:Agent",
      "Agent"
    ]
  },
  "hasBeenPublishedBy": [
    {
      "@id": "https://data.datatourisme.fr/cbc8f135-bec8-365b-8b02-ea7abf78dfa7",
      "schema:legalName": "SIT Breton",
      "@type": [
        "schema:Organization",
        "foaf:Agent",
        "Agent"
      ]
    }
  ],
  "hasContact": [
    {
      "@id": "https://data.datatourisme.fr/237c1a86-1950-3c67-8b63-4129bfd6b484",
      "schema:telephone": [
        "+33 2 97 33 60 56"
      ],
      "@type": [
        "foaf:Agent",
        "Agent"
      ],
      "foaf:homepage": [
        "http://kerguelen-equitation.fr/"
      ]
    }
  ],
  "hasDescription": [
    {
      "@id": "https://data.datatourisme.fr/77a73772-7cae-309a-819a-86af3d56eb61",
      "dc:description": {
        "de": [
          "Kommen Sie, um zu praktizieren und besondere Momente mit unseren Pferden und Ponys zu teilen. Wir sind das ganze Jahr über geöffnet. Wir verfügen über eine Kavallerie und ein qualifiziertes Team, um Ihnen ein sicheres und angenehmes Reiten zu ermöglichen. In Kursen: zu jeder Schulferienzeit. Für Kinder ab 4 Jahren, Jugendliche und Erwachsene. Ablegen der eidgenössischen Galopps. Gruppen- und Privatunterricht. Das ganze Jahr über Ausritte für Kinder von 3 bis 6 Jahren nach Vereinbarung. Im Juli/August: Ausritte ab 10 Jahren."
        ],
        "en": [
          "Come and practice and share privileged moments with our horses and ponies. We are open all year round. We have a qualified team of horsemen and women for a safe and enjoyable practice. In training course : at each period of school vacations. For children from 4 years old, for teenagers and adults. Passing of the federal gallops. Group and private lessons. All year round, hand held rides for 3/6 year olds by appointment. In July/August, rides for 10 year olds and up."
        ],
        "it": [
          "Venite a fare pratica e a condividere momenti speciali con i nostri cavalli e pony. Siamo aperti tutto l'anno. Abbiamo un team di cavalieri e personale qualificato per un'equitazione sicura e divertente. Nei corsi di formazione: durante ogni periodo di vacanza scolastica. Per bambini a partire dai 4 anni, per adolescenti e adulti. Passaggio dei galoppini federali. Lezioni di gruppo e private. Tutto l'anno, passeggiate per bambini di 3/6 anni su appuntamento. In luglio/agosto, giostre per bambini dai 10 anni in su."
        ],
        "fr": [
          "Venez pratiquer et partager des moments privilégiés avec nos chevaux et poneys. Nous sommes ouverts toute l'année. Nous disposons d'une cavalerie et d'une équipe qualifiée pour une pratique plaisir en toute sécurité.A l'année : en loisir ou en compétition. En stage : à chaque période de vacances scolaires. Pour les enfants dès 4 ans, pour les ados et les adultes. Passage des galops fédéraux. Cours collectifs et particuliers. Toute l'année, balade en main pour les 3/6 ans sur rdv. En juillet/août, balade dès 10 ans."
        ],
        "es": [
          "Ven a practicar y a compartir momentos especiales con nuestros caballos y ponis. Estamos abiertos todo el año. Contamos con un equipo cualificado de jinetes y amazonas para una experiencia segura y agradable. En los cursos de formación: durante cada periodo de vacaciones escolares. Para niños a partir de 4 años, adolescentes y adultos. Paso de los galopes federales. Clases particulares y en grupo. Todo el año, paseos para niños de 3/6 años con cita previa. En julio/agosto, paseos a partir de 10 años."
        ],
        "nl": [
          "Kom oefenen en deel bijzondere momenten met onze paarden en pony's. We zijn het hele jaar open. Wij hebben een gekwalificeerd team van ruiters en amazones voor een veilige en plezierige ervaring. In opleidingen: tijdens elke schoolvakantieperiode. Voor kinderen vanaf 4 jaar, voor tieners en volwassenen. Het passeren van de federale galop. Groeps- en privélessen. Het hele jaar door, ritten voor 3/6 jarigen op afspraak. In juli/augustus, ritten voor kinderen vanaf 10 jaar."
        ]
      },
      "@type": [
        "Description"
      ],
      "hasTranslatedProperty": [
        {
          "@id": "https://data.datatourisme.fr/0fb3549b-023b-38f3-a730-8292406bf3af",
          "dc:contributor": [
            "https://api.deepl.com/v2/translate"
          ],
          "rdf:language": [
            "en"
          ],
          "rdf:predicate": [
            {
              "@id": "dc:description"
            }
          ]
        },
        {
          "@id": "https://data.datatourisme.fr/49cedd42-84f1-31e8-b32a-9154e0b25602",
          "dc:contributor": [
            "https://api.deepl.com/v2/translate"
          ],
          "rdf:language": [
            "nl"
          ],
          "rdf:predicate": [
            {
              "@id": "dc:description"
            }
          ]
        },
        {
          "@id": "https://data.datatourisme.fr/9a54362e-d82d-3b42-9f93-18bedab482e8",
          "dc:contributor": [
            "https://api.deepl.com/v2/translate"
          ],
          "rdf:language": [
            "de"
          ],
          "rdf:predicate": [
            {
              "@id": "dc:description"
            }
          ]
        },
        {
          "@id": "https://data.datatourisme.fr/bebde879-40c0-37c1-a33c-527a9e2c03d1",
          "dc:contributor": [
            "https://api.deepl.com/v2/translate"
          ],
          "rdf:language": [
            "es"
          ],
          "rdf:predicate": [
            {
              "@id": "dc:description"
            }
          ]
        },
        {
          "@id": "https://data.datatourisme.fr/d3289f5b-c954-3208-b150-e3d7664e790e",
          "dc:contributor": [
            "https://api.deepl.com/v2/translate"
          ],
          "rdf:language": [
            "it"
          ],
          "rdf:predicate": [
            {
              "@id": "dc:description"
            }
          ]
        }
      ]
    }
  ],
  "hasTheme": [
    {
      "@id": "kb:Riding",
      "@type": [
        "SportsTheme"
      ],
      "rdfs:label": {
        "de": [
          "Reiten"
        ],
        "pt": [
          "Equitação"
        ],
        "en": [
          "Riding"
        ],
        "it": [
          "Equitazione"
        ],
        "fr": [
          "Equitation"
        ],
        "nl": [
          "Paardrijden"
        ],
        "es": [
          "Equitación"
        ]
      }
    }
  ],
  "isLocatedAt": [
    {
      "@id": "https://data.datatourisme.fr/a00fdf64-dd5c-3371-a591-c113b800f6b6",
      "schema:address": [
        {
          "@id": "https://data.datatourisme.fr/7ad28e03-c422-3bfa-9504-aa0158f1fa5b",
          "schema:addressLocality": "Larmor-Plage",
          "schema:postalCode": "56260",
          "schema:streetAddress": [
            "Kerguelen"
          ],
          "@type": [
            "schema:PostalAddress",
            "PostalAddress"
          ],
          "hasAddressCity": {
            "@id": "kb:56107",
            "@type": [
              "City"
            ],
            "rdfs:label": {
              "de": [
                "Larmor-Plage"
              ],
              "pt": [
                "Larmor-Plage"
              ],
              "en": [
                "Larmor-Plage"
              ],
              "it": [
                "Larmor-Plage"
              ],
              "fr": [
                "Larmor-Plage"
              ],
              "nl": [
                "Larmor-Plage"
              ],
              "es": [
                "Larmor-Plage"
              ]
            },
            "insee": "56107",
            "isPartOfDepartment": {
              "@id": "kb:France5356",
              "@type": [
                "Department"
              ],
              "rdfs:label": {
                "de": [
                  "Morbihan"
                ],
                "pt": [
                  "Morbihan"
                ],
                "en": [
                  "Morbihan"
                ],
                "it": [
                  "Morbihan"
                ],
                "fr": [
                  "Morbihan"
                ],
                "nl": [
                  "Morbihan"
                ],
                "es": [
                  "Morbihan"
                ]
              },
              "insee": "56",
              "isPartOfRegion": {
                "@id": "kb:France53",
                "@type": [
                  "Region"
                ],
                "rdfs:label": {
                  "de": [
                    "Bretagne"
                  ],
                  "pt": [
                    "Bretagne"
                  ],
                  "en": [
                    "Bretagne"
                  ],
                  "it": [
                    "Bretagne"
                  ],
                  "fr": [
                    "Bretagne"
                  ],
                  "nl": [
                    "Bretagne"
                  ],
                  "es": [
                    "Bretagne"
                  ]
                },
                "insee": "53",
                "isPartOfCountry": {
                  "@id": "kb:France",
                  "@type": [
                    "schema:Country"
                  ],
                  "rdfs:label": {
                    "de": [
                      "France",
                      "Frankreich"
                    ],
                    "pt": [
                      "França",
                      "France"
                    ],
                    "en": [
                      "France"
                    ],
                    "it": [
                      "France",
                      "Francia"
                    ],
                    "fr": [
                      "France"
                    ],
                    "nl": [
                      "France",
                      "Frankrijk"
                    ],
                    "es": [
                      "France",
                      "Francia"
                    ]
                  }
                }
              }
            }
          }
        }
      ],
      "schema:geo": {
        "@id": "https://data.datatourisme.fr/a31070cc-9fdd-3dfc-99c2-5fc603c4e8eb",
        "schema:latitude": "47.70774",
        "schema:longitude": "-3.403575",
        "@type": [
          "schema:GeoCoordinates"
        ]
      },
      "@type": [
        "schema:Place",
        "Place"
      ]
    }
  ],
  "lastUpdate": "2026-05-11",
  "lastUpdateDatatourisme": "2026-05-12T03:20:43.28Z"
}