{
  "@id": "https://data.datatourisme.fr/38/e97a7dce-11e4-3caa-9c55-02af024246ec",
  "dc:identifier": "HPAf135639128394",
  "@type": [
    "schema:Accommodation",
    "schema:LodgingBusiness",
    "Accommodation",
    "CamperVanArea",
    "Camping",
    "CampingAndCaravanning",
    "PlaceOfInterest",
    "PointOfInterest"
  ],
  "rdfs:label": {
    "en": [
      "Camping La Ferme de Lann Hoëdic"
    ],
    "fr": [
      "Camping La Ferme de Lann Hoëdic"
    ]
  },
  "COVID19SpecialMeasures": {
    "de": [
      "Von der FDHPA ausgehandeltes Gesundheitsprotokoll"
    ],
    "en": [
      "Protocole sanitaire négocié par la FDHPA"
    ],
    "it": [
      "Protocollo sanitario negoziato dalla FDHPA"
    ],
    "fr": [
      "Protocole sanitaire négocié par la FDHPA"
    ],
    "es": [
      "Protocolo sanitario negociado por la FDHPA"
    ],
    "nl": [
      "Door de FDHPA overeengekomen gezondheidsprotocol"
    ]
  },
  "hasBeenCreatedBy": {
    "@id": "https://data.datatourisme.fr/c35edcbe-0c90-31e4-9f91-0387a16a7c7f",
    "schema:legalName": "CRT Bretagne_",
    "@type": [
      "schema:Organization",
      "foaf:Agent",
      "Agent"
    ]
  },
  "hasBeenPublishedBy": [
    {
      "@id": "https://data.datatourisme.fr/cbc8f135-bec8-365b-8b02-ea7abf78dfa7",
      "schema:legalName": "SIT Breton",
      "@type": [
        "schema:Organization",
        "foaf:Agent",
        "Agent"
      ]
    }
  ],
  "hasContact": [
    {
      "@id": "https://data.datatourisme.fr/c15e23be-eb10-3846-a82d-879b97cb6da8",
      "schema:telephone": [
        "+33 2 97 48 01 73"
      ],
      "@type": [
        "foaf:Agent",
        "Agent"
      ],
      "foaf:homepage": [
        "http://www.camping-lannhoedic.fr/"
      ]
    }
  ],
  "hasDescription": [
    {
      "@id": "https://data.datatourisme.fr/e5d3e022-d15c-3521-86b9-1806fd02da4d",
      "dc:description": {
        "de": [
          "Freilufthotelgewerbe"
        ],
        "en": [
          "Hôtellerie de plein air"
        ],
        "it": [
          "Hotel all'aperto"
        ],
        "fr": [
          "Hôtellerie de plein air"
        ],
        "nl": [
          "Openluchthotels"
        ],
        "es": [
          "Hoteles al aire libre"
        ]
      },
      "@type": [
        "Description"
      ],
      "hasTranslatedProperty": [
        {
          "@id": "https://data.datatourisme.fr/2cd6e3ea-557d-3429-b5d6-2ce6a742f8e8",
          "dc:contributor": [
            "https://api.deepl.com/v2/translate"
          ],
          "rdf:language": [
            "de"
          ],
          "rdf:predicate": [
            {
              "@id": "dc:description"
            }
          ]
        },
        {
          "@id": "https://data.datatourisme.fr/6fe6a55f-4314-36de-a9c4-4e183fcecfa9",
          "dc:contributor": [
            "https://api.deepl.com/v2/translate"
          ],
          "rdf:language": [
            "nl"
          ],
          "rdf:predicate": [
            {
              "@id": "dc:description"
            }
          ]
        },
        {
          "@id": "https://data.datatourisme.fr/9bbb84f2-8f97-3109-ac95-4148a3a98ded",
          "dc:contributor": [
            "https://api.deepl.com/v2/translate"
          ],
          "rdf:language": [
            "es"
          ],
          "rdf:predicate": [
            {
              "@id": "dc:description"
            }
          ]
        },
        {
          "@id": "https://data.datatourisme.fr/f6ce4c71-76d1-3da6-9828-14b4672c8944",
          "dc:contributor": [
            "https://api.deepl.com/v2/translate"
          ],
          "rdf:language": [
            "it"
          ],
          "rdf:predicate": [
            {
              "@id": "dc:description"
            }
          ]
        }
      ]
    }
  ],
  "hasExternalReference": [
    {
      "@id": "https://data.datatourisme.fr/5c8f9826-119b-3aab-b176-9c2804e43394",
      "@type": [
        "ExternalReference"
      ],
      "hasExternalIdentifier": "NH86GNPPWMH2",
      "hasExternalPlatform": [
        {
          "@id": "kb:ReferentielNationalBatiments",
          "@type": [
            "ExternalPlatform"
          ],
          "rdfs:comment": {
            "de": [
              "Ein digitaler öffentlicher Dienst, der eine nationale Gebäude-Referenz erstellt."
            ],
            "pt": [
              "Serviço público digital que cria uma referência nacional de edifícios."
            ],
            "en": [
              "A digital public service creating a national building reference."
            ],
            "it": [
              "Servizio pubblico digitale che crea un riferimento nazionale degli edifici."
            ],
            "fr": [
              "Service public numérique créant une référence nationale du bâtiment."
            ],
            "es": [
              "Un servicio público digital que crea una referencia nacional de edificios."
            ],
            "nl": [
              "Een digitale openbare dienst die een nationale gebouwreferentie creëert."
            ]
          },
          "rdfs:label": {
            "de": [
              "Nationales Gebäude-Referenzsystem"
            ],
            "pt": [
              "Normas nacionais de construção"
            ],
            "en": [
              "National Building Standards"
            ],
            "it": [
              "Standard edilizi nazionali"
            ],
            "fr": [
              "Référentiel National des Bâtiments"
            ],
            "es": [
              "Normas nacionales de construcción"
            ],
            "nl": [
              "Nationale bouwnorm"
            ]
          },
          "hasExternalPlatformUrl": "https://rnb.beta.gouv.fr"
        }
      ]
    }
  ],
  "hasReview": [
    {
      "@id": "https://data.datatourisme.fr/7724dbf0-7649-358b-be17-1db1b66a240f",
      "@type": [
        "Review"
      ],
      "hasReviewValue": {
        "@id": "kb:ScaleRating_3etoiles",
        "schema:ratingValue": "3.0",
        "@type": [
          "ScaleRating"
        ],
        "rdfs:label": {
          "de": [
            "3 Sterne"
          ],
          "pt": [
            "3 estrelas"
          ],
          "en": [
            "3 Stars"
          ],
          "it": [
            "3 stelle"
          ],
          "fr": [
            "3 étoiles"
          ],
          "nl": [
            "3 sterren"
          ],
          "es": [
            "3 estrellas"
          ]
        },
        "isCompliantWith": [
          "CampingAndCaravanning",
          "ClubOrHolidayVillage",
          "HolidayCentre",
          "Hotel",
          "SelfCateringAccommodation"
        ]
      }
    }
  ],
  "hasTranslatedProperty": [
    {
      "@id": "https://data.datatourisme.fr/3ef485a3-fcd4-3a8d-90f3-0ff585620e0e",
      "dc:contributor": [
        "https://api.deepl.com/v2/translate"
      ],
      "rdf:language": [
        "nl"
      ],
      "rdf:predicate": [
        "COVID19SpecialMeasures"
      ]
    },
    {
      "@id": "https://data.datatourisme.fr/4cd97ab1-ede3-3c23-a2bb-149c206c2bed",
      "dc:contributor": [
        "https://api.deepl.com/v2/translate"
      ],
      "rdf:language": [
        "de"
      ],
      "rdf:predicate": [
        "COVID19SpecialMeasures"
      ]
    },
    {
      "@id": "https://data.datatourisme.fr/bda0bcb0-f772-3aff-9175-ff7b2bdffc80",
      "dc:contributor": [
        "https://api.deepl.com/v2/translate"
      ],
      "rdf:language": [
        "it"
      ],
      "rdf:predicate": [
        "COVID19SpecialMeasures"
      ]
    },
    {
      "@id": "https://data.datatourisme.fr/e8fd3c4c-bd3b-3bfb-afd1-58cb3b0b18ab",
      "dc:contributor": [
        "https://api.deepl.com/v2/translate"
      ],
      "rdf:language": [
        "es"
      ],
      "rdf:predicate": [
        "COVID19SpecialMeasures"
      ]
    }
  ],
  "isLocatedAt": [
    {
      "@id": "https://data.datatourisme.fr/30fbc438-8acc-3736-93de-ea2fc4f3b987",
      "schema:address": [
        {
          "@id": "https://data.datatourisme.fr/64b0954b-7105-3f61-8b4c-183ffa737701",
          "schema:addressLocality": "Sarzeau",
          "schema:postalCode": "56370",
          "schema:streetAddress": [
            "Lann Hoëdic",
            "Rue Jean de la Fontaine"
          ],
          "@type": [
            "schema:PostalAddress",
            "PostalAddress"
          ],
          "hasAddressCity": {
            "@id": "kb:56240",
            "@type": [
              "City"
            ],
            "rdfs:label": {
              "de": [
                "Sarzeau"
              ],
              "pt": [
                "Sarzeau"
              ],
              "en": [
                "Sarzeau"
              ],
              "it": [
                "Sarzeau"
              ],
              "fr": [
                "Sarzeau"
              ],
              "nl": [
                "Sarzeau"
              ],
              "es": [
                "Sarzeau"
              ]
            },
            "insee": "56240",
            "isPartOfDepartment": {
              "@id": "kb:France5356",
              "@type": [
                "Department"
              ],
              "rdfs:label": {
                "de": [
                  "Morbihan"
                ],
                "pt": [
                  "Morbihan"
                ],
                "en": [
                  "Morbihan"
                ],
                "it": [
                  "Morbihan"
                ],
                "fr": [
                  "Morbihan"
                ],
                "nl": [
                  "Morbihan"
                ],
                "es": [
                  "Morbihan"
                ]
              },
              "insee": "56",
              "isPartOfRegion": {
                "@id": "kb:France53",
                "@type": [
                  "Region"
                ],
                "rdfs:label": {
                  "de": [
                    "Bretagne"
                  ],
                  "pt": [
                    "Bretagne"
                  ],
                  "en": [
                    "Bretagne"
                  ],
                  "it": [
                    "Bretagne"
                  ],
                  "fr": [
                    "Bretagne"
                  ],
                  "nl": [
                    "Bretagne"
                  ],
                  "es": [
                    "Bretagne"
                  ]
                },
                "insee": "53",
                "isPartOfCountry": {
                  "@id": "kb:France",
                  "@type": [
                    "schema:Country"
                  ],
                  "rdfs:label": {
                    "de": [
                      "France",
                      "Frankreich"
                    ],
                    "pt": [
                      "França",
                      "France"
                    ],
                    "en": [
                      "France"
                    ],
                    "it": [
                      "France",
                      "Francia"
                    ],
                    "fr": [
                      "France"
                    ],
                    "nl": [
                      "France",
                      "Frankrijk"
                    ],
                    "es": [
                      "France",
                      "Francia"
                    ]
                  }
                }
              }
            }
          }
        }
      ],
      "schema:geo": {
        "@id": "https://data.datatourisme.fr/9de8efe4-71a3-3fe0-8d29-e71e8f2069b2",
        "schema:latitude": "47.50597",
        "schema:longitude": "-2.762667",
        "@type": [
          "schema:GeoCoordinates"
        ]
      },
      "@type": [
        "schema:Place",
        "Place"
      ]
    }
  ],
  "lastUpdate": "2026-03-04",
  "lastUpdateDatatourisme": "2026-03-05T04:04:22.074Z"
}